sqlmodel_react_admin/client.py
sqlmodel_react_admin/models.py
sqlmodel_react_admin/routers.py
sqlmodel_react_admin-0.0.6.dist-info/LICENSE
sqlmodel_react_admin-0.0.6.dist-info/METADATA
sqlmodel_react_admin-0.0.6.dist-info/WHEEL
sqlmodel_react_admin-0.0.6.dist-info/RECORD
